embedly_cards/__init__.py
embedly_cards/card_markdown.py
embedly_cards/card_rst.py
embedly_cards-0.2.0.dist-info/WHEEL
embedly_cards-0.2.0.dist-info/metadata.json
embedly_cards-0.2.0.dist-info/DESCRIPTION.rst
embedly_cards-0.2.0.dist-info/METADATA
embedly_cards-0.2.0.dist-info/top_level.txt
embedly_cards-0.2.0.dist-info/RECORD
