Metadata-Version: 2.0
Name: embedly-cards
Version: 0.2.0
Summary: Pelican plugin for embedding external content using Embed.ly Cards
Home-page: https://github.com/josh146/embedly_cards
Author: Josh Izaac
Author-email: josh@iza.ac
License: GPLv3
Download-URL: https://github.com/josh146/embedly_cards/archive/0.2.0.zip
Platform: UNKNOWN
Classifier: Development Status :: 5 - Production/Stable
Classifier: Environment :: Console
Classifier: Intended Audience :: Developers
Classifier: License :: OSI Approved :: GNU General Public License v3 (GPLv3)
Classifier: Natural Language :: English
Classifier: Operating System :: OS Independent
Classifier: Operating System :: MacOS :: MacOS X
Classifier: Operating System :: POSIX :: Linux
Classifier: Programming Language :: Python
Classifier: Topic :: Internet :: WWW/HTTP
Classifier: Topic :: Software Development :: Libraries :: Python Modules
Classifier: Topic :: Text Processing
Provides: embedly_cards
Requires-Dist: docutils
Requires-Dist: pelican
